recommonmark/__init__.py
recommonmark/parser.py
recommonmark/scripts.py
recommonmark/states.py
recommonmark/transform.py
recommonmark-0.7.0.dist-info/METADATA
recommonmark-0.7.0.dist-info/WHEEL
recommonmark-0.7.0.dist-info/entry_points.txt
recommonmark-0.7.0.dist-info/top_level.txt
recommonmark-0.7.0.dist-info/RECORD
