Metadata-Version: 1.1
Name: recommonmark
Version: 0.7.0
Summary: A docutils-compatibility bridge to CommonMark, enabling you to write CommonMark inside of Docutils & Sphinx projects.
Home-page: https://github.com/rtfd/recommonmark
Author: UNKNOWN
Author-email: UNKNOWN
License: MIT
Platform: UNKNOWN
Classifier: License :: OSI Approved :: MIT License
